huaweicloudsdkcodehub/__init__.py
huaweicloudsdkcodehub/v3/__init__.py
huaweicloudsdkcodehub/v3/codehub_async_client.py
huaweicloudsdkcodehub/v3/codehub_client.py
huaweicloudsdkcodehub/v3/model/__init__.py
huaweicloudsdkcodehub/v3/model/add_deploy_key_request.py
huaweicloudsdkcodehub/v3/model/add_deploy_key_request_body.py
huaweicloudsdkcodehub/v3/model/add_deploy_key_response.py
huaweicloudsdkcodehub/v3/model/add_deploy_key_v2_request.py
huaweicloudsdkcodehub/v3/model/add_deploy_key_v2_response.py
huaweicloudsdkcodehub/v3/model/add_hooks_request.py
huaweicloudsdkcodehub/v3/model/add_hooks_response.py
huaweicloudsdkcodehub/v3/model/add_protect_access_level.py
huaweicloudsdkcodehub/v3/model/add_protect_branch_v2_request.py
huaweicloudsdkcodehub/v3/model/add_protect_branch_v2_response.py
huaweicloudsdkcodehub/v3/model/add_protect_request.py
huaweicloudsdkcodehub/v3/model/add_protect_response.py
huaweicloudsdkcodehub/v3/model/add_repo_members_request.py
huaweicloudsdkcodehub/v3/model/add_repo_members_response.py
huaweicloudsdkcodehub/v3/model/add_ssh_key_request.py
huaweicloudsdkcodehub/v3/model/add_ssh_key_request_body.py
huaweicloudsdkcodehub/v3/model/add_ssh_key_response.py
huaweicloudsdkcodehub/v3/model/add_tag_v2_request.py
huaweicloudsdkcodehub/v3/model/add_tag_v2_response.py
huaweicloudsdkcodehub/v3/model/add_tags_request.py
huaweicloudsdkcodehub/v3/model/add_tags_response.py
huaweicloudsdkcodehub/v3/model/approval_action_type_dto.py
huaweicloudsdkcodehub/v3/model/approval_merge_request_approvers_item.py
huaweicloudsdkcodehub/v3/model/approval_user_dto.py
huaweicloudsdkcodehub/v3/model/approver_basic_dto.py
huaweicloudsdkcodehub/v3/model/associate_issues_request.py
huaweicloudsdkcodehub/v3/model/associate_issues_request_body.py
huaweicloudsdkcodehub/v3/model/associate_issues_response.py
huaweicloudsdkcodehub/v3/model/author.py
huaweicloudsdkcodehub/v3/model/branch.py
huaweicloudsdkcodehub/v3/model/branch_list.py
huaweicloudsdkcodehub/v3/model/branch_response.py
huaweicloudsdkcodehub-3.1.172.dist-info/METADATA
huaweicloudsdkcodehub-3.1.172.dist-info/WHEEL
huaweicloudsdkcodehub-3.1.172.dist-info/licenses/LICENSE
huaweicloudsdkcodehub-3.1.172.dist-info/RECORD
